Metadata-Version: 1.1
Name: hambot
Version: 1.0.0
Summary: HamBot - Slack Amateur (Ham) Radio Bot
Home-page: https://github.com/ampledata/hambot
Author: Greg Albrecht
Author-email: oss@undef.net
License: Copyright 2017 Greg Albrecht
